.pylintrc
AUTHORS
ChangeLog
README.rst
Vagrantfile
makefile
requirements.txt
setup.cfg
setup.py
bin/example_consumer.py
bin/example_publisher.py
pika_consumer/__init__.py
pika_consumer.egg-info/PKG-INFO
pika_consumer.egg-info/SOURCES.txt
pika_consumer.egg-info/dependency_links.txt
pika_consumer.egg-info/not-zip-safe
pika_consumer.egg-info/pbr.json
pika_consumer.egg-info/requires.txt
pika_consumer.egg-info/top_level.txt
playbooks/main.yml
playbooks/roles/example-pika-consumer/defaults/main.yml
playbooks/roles/example-pika-consumer/meta/main.yml
playbooks/roles/example-pika-consumer/tasks/main.yml
playbooks/roles/example-pika-consumer/templates/example-pika-consumer.service
playbooks/roles/pyenv/defaults/main.yml
playbooks/roles/pyenv/tasks/main.yml
playbooks/roles/rabbitmq/defaults/main.yml
playbooks/roles/rabbitmq/files/etc/default/rabbitmq-server
playbooks/roles/rabbitmq/files/etc/logrotate.d/rabbitmq-server
playbooks/roles/rabbitmq/handlers/main.yml
playbooks/roles/rabbitmq/meta/main.yml
playbooks/roles/rabbitmq/tasks/clustering.yml
playbooks/roles/rabbitmq/tasks/configure.yml
playbooks/roles/rabbitmq/tasks/cookie.yml
playbooks/roles/rabbitmq/tasks/install.yml
playbooks/roles/rabbitmq/tasks/main.yml
playbooks/roles/rabbitmq/tasks/plugins.yml
playbooks/roles/rabbitmq/templates/etc/rabbitmq/rabbitmq.config.j2