Metadata-Version: 1.1
Name: pika-consumer
Version: 0.0.5
Summary: A pika consumer class which may be used to create rabbitmq queue consumers
Home-page: http://github.com/schlueter/pika-consumer
Author: Brandon Schlueter
Author-email: pika-consumer@schlueter.blue
License: GNU Affero General Public License v3 or later (AGPLv3+)
Platform: UNKNOWN
Classifier: Environment :: OpenStack
Classifier: Intended Audience :: Information Technology
Classifier: Intended Audience :: System Administrators
Classifier: License :: OSI Approved :: GNU Affero General Public License v3 or later (AGPLv3+)
Classifier: Operating System :: POSIX :: Linux
Classifier: Operating System :: MacOS :: MacOS X
Classifier: Programming Language :: Python
Classifier: Programming Language :: Python :: 3.6
